{
  "checked": 50,
  "updated_count": 5,
  "player_form_saved": 43,
  "updated": [
    {
      "race_key": "winticket:2026071022:2:10",
      "finish_order": [
        1,
        9,
        3,
        8,
        5,
        2,
        4,
        7,
        6
      ]
    },
    {
      "race_key": "winticket:2026071022:2:9",
      "finish_order": [
        5,
        9,
        3,
        2,
        8,
        7,
        6,
        1,
        4
      ]
    },
    {
      "race_key": "winticket:2026071022:2:8",
      "finish_order": [
        1,
        2,
        8,
        4,
        9,
        7,
        5,
        6,
        3
      ]
    },
    {
      "race_key": "winticket:2026071022:2:7",
      "finish_order": [
        2,
        5,
        1,
        4,
        7,
        6,
        3,
        8
      ]
    },
    {
      "race_key": "winticket:2026071022:2:6",
      "finish_order": [
        7,
        1,
        3,
        5,
        8,
        6,
        2,
        4
      ]
    }
  ],
  "skipped_count": 45,
  "skipped": [
    {
      "race_key": "winticket:2026071042:2:9",
      "reason": "result not decided"
    },
    {
      "race_key": "winticket:2026071042:2:8",
      "reason": "result not decided"
    },
    {
      "race_key": "winticket:2026071042:2:7",
      "reason": "result not decided"
    },
    {
      "race_key": "winticket:2026071042:2:6",
      "reason": "result not decided"
    },
    {
      "race_key": "winticket:2026071042:2:5",
      "reason": "result not decided"
    },
    {
      "race_key": "winticket:2026071042:2:4",
      "reason": "result not decided"
    },
    {
      "race_key": "winticket:2026071042:2:2",
      "reason": "result not decided"
    },
    {
      "race_key": "winticket:2026071042:2:3",
      "reason": "result not decided"
    },
    {
      "race_key": "winticket:2026071042:2:1",
      "reason": "result not decided"
    },
    {
      "race_key": "winticket:2026071175:1:10",
      "reason": "result not decided"
    },
    {
      "race_key": "winticket:2026071175:1:11",
      "reason": "result not decided"
    },
    {
      "race_key": "winticket:2026071175:1:9",
      "reason": "result not decided"
    },
    {
      "race_key": "winticket:2026071175:1:8",
      "reason": "result not decided"
    },
    {
      "race_key": "winticket:2026071175:1:7",
      "reason": "result not decided"
    },
    {
      "race_key": "winticket:2026071175:1:6",
      "reason": "result not decided"
    },
    {
      "race_key": "winticket:2026071175:1:5",
      "reason": "result not decided"
    },
    {
      "race_key": "winticket:2026071175:1:4",
      "reason": "result not decided"
    },
    {
      "race_key": "winticket:2026071175:1:3",
      "reason": "result not decided"
    },
    {
      "race_key": "winticket:2026071175:1:2",
      "reason": "result not decided"
    },
    {
      "race_key": "winticket:2026071175:1:1",
      "reason": "result not decided"
    },
    {
      "race_key": "winticket:2026071022:2:12",
      "reason": "result not decided"
    },
    {
      "race_key": "winticket:2026071022:2:11",
      "reason": "result not decided"
    },
    {
      "race_key": "winticket:2026071013:2:8",
      "reason": "result not decided"
    },
    {
      "race_key": "winticket:2026071013:2:9",
      "reason": "result not decided"
    },
    {
      "race_key": "winticket:2026071013:2:7",
      "reason": "result not decided"
    },
    {
      "race_key": "winticket:2026071013:2:6",
      "reason": "result not decided"
    },
    {
      "race_key": "winticket:2026071013:2:5",
      "reason": "result not decided"
    },
    {
      "race_key": "winticket:2026071013:2:4",
      "reason": "result not decided"
    },
    {
      "race_key": "winticket:2026071013:2:3",
      "reason": "result not decided"
    },
    {
      "race_key": "winticket:2026071013:2:2",
      "reason": "result not decided"
    },
    {
      "race_key": "winticket:2026071013:2:1",
      "reason": "result not decided"
    },
    {
      "race_key": "winticket:2026071037:2:12",
      "reason": "result not decided"
    },
    {
      "race_key": "winticket:2026071037:2:11",
      "reason": "result not decided"
    },
    {
      "race_key": "winticket:2026071037:2:10",
      "reason": "result not decided"
    },
    {
      "race_key": "winticket:2026071037:2:9",
      "reason": "result not decided"
    },
    {
      "race_key": "winticket:2026071037:2:8",
      "reason": "result not decided"
    },
    {
      "race_key": "winticket:2026071037:2:7",
      "reason": "result not decided"
    },
    {
      "race_key": "winticket:2026071037:2:6",
      "reason": "result not decided"
    },
    {
      "race_key": "winticket:2026071037:2:5",
      "reason": "result not decided"
    },
    {
      "race_key": "winticket:2026071037:2:4",
      "reason": "result not decided"
    },
    {
      "race_key": "winticket:2026071037:2:3",
      "reason": "result not decided"
    },
    {
      "race_key": "winticket:2026071037:2:2",
      "reason": "result not decided"
    },
    {
      "race_key": "winticket:2026071037:2:1",
      "reason": "result not decided"
    },
    {
      "race_key": "winticket:2026071143:1:12",
      "reason": "result not decided"
    },
    {
      "race_key": "winticket:2026071143:1:11",
      "reason": "result not decided"
    }
  ],
  "status": {
    "races": 750,
    "entries": 5117,
    "result_races": 695,
    "result_entries": 4675,
    "predictions": 1270,
    "documents": 15,
    "db_path": "/home/runner/work/keirin-ai-lab/keirin-ai-lab/data/keirin_learning.sqlite3"
  },
  "model_training": {
    "rows": 4675,
    "races": 695,
    "positive_rows": 651,
    "best_iteration": 5,
    "valid_races": 105
  }
}